{
  "users": [
    {
      "name": "Vishal Patil",
      "username": "vishal7860",
      "password": "123456",
      "guardiantype": "father",
      "gname": "Tejrao",
      "address": "Pune",
      "citizenship": "Indian",
      "inputCountry": 3,
      "state": "13",
      "email": "vishalpatil7860@gmail.com",
      "gender": "male",
      "maritialstatus": "unmarried",
      "contact": "9049620687",
      "dob": "2021-05-09",
      "registerDate": "2021-05-09",
      "accountType": "saving",
      "branch": "Hadapsar",
      "citizen": "Minor",
      "deposit": "5000",
      "prooftype": "pan",
      "docnumber": "AA11AA11AA11",
      "refername": "deepa",
      "refernumber": "22222",
      "referaddress": "Pune",
      "cid": "R-505",
      "id": 6
    },
    {
      "name": "Vishal Patil",
      "username": "vishal_t_patil",
      "password": "123456",
      "guardiantype": "father",
      "gname": "Tejrao",
      "address": "Pune",
      "citizenship": "Indian",
      "inputCountry": "5",
      "state": "15",
      "email": "vishalpatil7860@gmail.com",
      "gender": "male",
      "maritialstatus": "unmarried",
      "contact": "9049620687",
      "dob": "2021-05-06",
      "registerDate": "2021-05-09",
      "accountType": "saving",
      "branch": "Hadapsar",
      "citizen": "Minor",
      "deposit": "5000",
      "prooftype": "aadhar",
      "docnumber": "AA11AA11AA11",
      "refername": "deepa",
      "refernumber": "121212",
      "referaddress": "PUNE",
      "cid": "R-880",
      "id": 7
    },
    {
      "name": "Vishal Patil",
      "username": "vishalpatil7860",
      "password": "123456",
      "guardiantype": "father",
      "gname": "Tejrao",
      "address": "Pune",
      "citizenship": "Indian",
      "inputCountry": "3",
      "state": "14",
      "email": "vishalpatil7860@gmail.com",
      "gender": "male",
      "maritialstatus": "unmarried",
      "contact": "9049620687",
      "dob": "1998-10-23",
      "registerDate": "2021-05-09",
      "accountType": "saving",
      "branch": "Hadapsar",
      "citizen": "Normal",
      "deposit": "5000",
      "prooftype": "pan",
      "docnumber": "AA11AA11AA11",
      "refername": "deepa",
      "refernumber": "22222",
      "referaddress": "Pune",
      "cid": "R-125",
      "id": 8
    },
    {
      "name": "",
      "username": "",
      "password": "",
      "guardiantype": "",
      "gname": "",
      "address": "",
      "citizenship": "",
      "inputCountry": 3,
      "state": "",
      "email": "",
      "gender": "",
      "maritialstatus": "",
      "contact": "",
      "dob": "",
      "registerDate": "2021-05-11",
      "accountType": "",
      "branch": "",
      "citizen": "",
      "deposit": "",
      "prooftype": "",
      "docnumber": "",
      "refername": "",
      "refernumber": "",
      "referaddress": "",
      "cid": "R-710",
      "id": 9
    },
    {
      "name": "",
      "username": "",
      "password": "",
      "guardiantype": "",
      "gname": "",
      "address": "",
      "citizenship": "",
      "inputCountry": 3,
      "state": "",
      "email": "",
      "gender": "",
      "maritialstatus": "",
      "contact": "",
      "dob": "",
      "registerDate": "2021-05-11",
      "accountType": "",
      "branch": "",
      "citizen": "",
      "deposit": "",
      "prooftype": "",
      "docnumber": "",
      "refername": "",
      "refernumber": "",
      "referaddress": "",
      "cid": "R-909",
      "id": 10
    },
    {
      "name": "Vishal",
      "username": "vp7860",
      "password": "123456",
      "guardiantype": "Father",
      "gname": "Tejrao",
      "address": "Pune",
      "citizenship": "Indian",
      "inputCountry": "India",
      "state": "Maharashtra",
      "email": "vp@gmail.com",
      "gender": "Male",
      "maritialstatus": "Unmarried",
      "contact": "9090909090",
      "dob": "23-10-1998",
      "registerDate": "11-05-2021",
      "accountType": "Savings",
      "branch": "Hadapsar",
      "citizen": "Normal",
      "deposit": "5000",
      "prooftype": "Pan card",
      "docnumber": "AA11AA11AA11",
      "refername": "Deepa",
      "refernumber": "123456789",
      "referaddress": "Pune",
      "cid": "R-397",
      "id": 11
    },
    {
      "name": "",
      "username": "",
      "password": "",
      "guardiantype": "",
      "gname": "",
      "address": "",
      "citizenship": "",
      "inputCountry": 3,
      "state": "",
      "email": "",
      "gender": "",
      "maritialstatus": "",
      "contact": "",
      "dob": "",
      "registerDate": "2021-05-11",
      "accountType": "",
      "branch": "",
      "citizen": "",
      "deposit": "",
      "prooftype": "",
      "docnumber": "",
      "refername": "",
      "refernumber": "",
      "referaddress": "",
      "cid": "R-817",
      "id": 12
    },
    {
      "name": "",
      "username": "",
      "password": "",
      "guardiantype": "",
      "gname": "",
      "address": "",
      "citizenship": "",
      "inputCountry": 3,
      "state": "",
      "email": "",
      "gender": "",
      "maritialstatus": "",
      "contact": "",
      "dob": "",
      "registerDate": "2021-05-11",
      "accountType": "",
      "branch": "",
      "citizen": "",
      "deposit": "",
      "prooftype": "",
      "docnumber": "",
      "refername": "",
      "refernumber": "",
      "referaddress": "",
      "cid": "R-807",
      "id": 13
    },
    {
      "name": "Vishal",
      "username": "vp7860",
      "password": "123456",
      "guardiantype": "Father",
      "gname": "Tejrao",
      "address": "Pune",
      "citizenship": "Indian",
      "inputCountry": "India",
      "state": "Maharashtra",
      "email": "vp@gmail.com",
      "gender": "Male",
      "maritialstatus": "Unmarried",
      "contact": "9090909090",
      "dob": "23-10-1998",
      "registerDate": "11-05-2021",
      "accountType": "Savings",
      "branch": "Hadapsar",
      "citizen": "Normal",
      "deposit": "5000",
      "prooftype": "Pan card",
      "docnumber": "AA11AA11AA11",
      "refername": "Deepa",
      "refernumber": "123456789",
      "referaddress": "Pune",
      "cid": "R-522",
      "id": 14
    },
    {
      "name": "",
      "username": "",
      "password": "",
      "guardiantype": "",
      "gname": "",
      "address": "",
      "citizenship": "",
      "inputCountry": 3,
      "state": "",
      "email": "",
      "gender": "",
      "maritialstatus": "",
      "contact": "",
      "dob": "",
      "registerDate": "2021-05-11",
      "accountType": "",
      "branch": "",
      "citizen": "",
      "deposit": "",
      "prooftype": "",
      "docnumber": "",
      "refername": "",
      "refernumber": "",
      "referaddress": "",
      "cid": "R-331",
      "id": 15
    },
    {
      "name": "",
      "username": "",
      "password": "",
      "guardiantype": "",
      "gname": "",
      "address": "",
      "citizenship": "",
      "inputCountry": 3,
      "state": "",
      "email": "",
      "gender": "",
      "maritialstatus": "",
      "contact": "",
      "dob": "",
      "registerDate": "2021-05-11",
      "accountType": "",
      "branch": "",
      "citizen": "",
      "deposit": "",
      "prooftype": "",
      "docnumber": "",
      "refername": "",
      "refernumber": "",
      "referaddress": "",
      "cid": "R-812",
      "id": 16
    },
    {
      "name": "",
      "username": "",
      "password": "",
      "guardiantype": "",
      "gname": "",
      "address": "",
      "citizenship": "",
      "inputCountry": 3,
      "state": "",
      "email": "",
      "gender": "",
      "maritialstatus": "",
      "contact": "",
      "dob": "",
      "registerDate": "2021-05-11",
      "accountType": "",
      "branch": "",
      "citizen": "",
      "deposit": "",
      "prooftype": "",
      "docnumber": "",
      "refername": "",
      "refernumber": "",
      "referaddress": "",
      "cid": "R-375",
      "id": 17
    },
    {
      "name": "",
      "username": "",
      "password": "",
      "guardiantype": "",
      "gname": "",
      "address": "",
      "citizenship": "",
      "inputCountry": 3,
      "state": "",
      "email": "",
      "gender": "",
      "maritialstatus": "",
      "contact": "",
      "dob": "",
      "registerDate": "2021-05-11",
      "accountType": "",
      "branch": "",
      "citizen": "",
      "deposit": "",
      "prooftype": "",
      "docnumber": "",
      "refername": "",
      "refernumber": "",
      "referaddress": "",
      "cid": "R-851",
      "id": 18
    },
    {
      "name": "Vishal",
      "username": "vp7860",
      "password": "123456",
      "guardiantype": "Father",
      "gname": "Tejrao",
      "address": "Pune",
      "citizenship": "Indian",
      "inputCountry": "India",
      "state": "Maharashtra",
      "email": "vp@gmail.com",
      "gender": "Male",
      "maritialstatus": "Unmarried",
      "contact": "9090909090",
      "dob": "23-10-1998",
      "registerDate": "11-05-2021",
      "accountType": "Savings",
      "branch": "Hadapsar",
      "citizen": "Normal",
      "deposit": "5000",
      "prooftype": "Pan card",
      "docnumber": "AA11AA11AA11",
      "refername": "Deepa",
      "refernumber": "123456789",
      "referaddress": "Pune",
      "cid": "R-338",
      "id": 19
    },
    {
      "name": "",
      "username": "",
      "password": "",
      "guardiantype": "",
      "gname": "",
      "address": "",
      "citizenship": "",
      "inputCountry": 3,
      "state": "",
      "email": "",
      "gender": "",
      "maritialstatus": "",
      "contact": "",
      "dob": "",
      "registerDate": "2021-05-11",
      "accountType": "",
      "branch": "",
      "citizen": "",
      "deposit": "",
      "prooftype": "",
      "docnumber": "",
      "refername": "",
      "refernumber": "",
      "referaddress": "",
      "cid": "R-880",
      "id": 20
    },
    {
      "name": "",
      "username": "",
      "password": "",
      "guardiantype": "",
      "gname": "",
      "address": "",
      "citizenship": "",
      "inputCountry": 3,
      "state": "",
      "email": "",
      "gender": "",
      "maritialstatus": "",
      "contact": "",
      "dob": "",
      "registerDate": "2021-05-11",
      "accountType": "",
      "branch": "",
      "citizen": "",
      "deposit": "",
      "prooftype": "",
      "docnumber": "",
      "refername": "",
      "refernumber": "",
      "referaddress": "",
      "cid": "R-380",
      "id": 21
    },
    {
      "name": "Vishal",
      "username": "vp7860",
      "password": "123456",
      "guardiantype": "Father",
      "gname": "Tejrao",
      "address": "Pune",
      "citizenship": "Indian",
      "inputCountry": "India",
      "state": "Maharashtra",
      "email": "vp@gmail.com",
      "gender": "Male",
      "maritialstatus": "Unmarried",
      "contact": "9090909090",
      "dob": "23-10-1998",
      "registerDate": "11-05-2021",
      "accountType": "Savings",
      "branch": "Hadapsar",
      "citizen": "Normal",
      "deposit": "5000",
      "prooftype": "Pan card",
      "docnumber": "AA11AA11AA11",
      "refername": "Deepa",
      "refernumber": "123456789",
      "referaddress": "Pune",
      "cid": "R-109",
      "id": 22
    },
    {
      "name": "",
      "username": "",
      "password": "",
      "guardiantype": "",
      "gname": "",
      "address": "",
      "citizenship": "",
      "inputCountry": 3,
      "state": "",
      "email": "",
      "gender": "",
      "maritialstatus": "",
      "contact": "",
      "dob": "",
      "registerDate": "2021-05-11",
      "accountType": "",
      "branch": "",
      "citizen": "",
      "deposit": "",
      "prooftype": "",
      "docnumber": "",
      "refername": "",
      "refernumber": "",
      "referaddress": "",
      "cid": "R-369",
      "id": 23
    },
    {
      "name": "",
      "username": "",
      "password": "",
      "guardiantype": "",
      "gname": "",
      "address": "",
      "citizenship": "",
      "inputCountry": 3,
      "state": "",
      "email": "",
      "gender": "",
      "maritialstatus": "",
      "contact": "",
      "dob": "",
      "registerDate": "2021-05-11",
      "accountType": "",
      "branch": "",
      "citizen": "",
      "deposit": "",
      "prooftype": "",
      "docnumber": "",
      "refername": "",
      "refernumber": "",
      "referaddress": "",
      "cid": "R-214",
      "id": 24
    },
    {
      "name": "Vishal",
      "username": "vp7860",
      "password": "123456",
      "guardiantype": "Father",
      "gname": "Tejrao",
      "address": "Pune",
      "citizenship": "Indian",
      "inputCountry": "India",
      "state": "Maharashtra",
      "email": "vp@gmail.com",
      "gender": "Male",
      "maritialstatus": "Unmarried",
      "contact": "9090909090",
      "dob": "23-10-1998",
      "registerDate": "11-05-2021",
      "accountType": "Savings",
      "branch": "Hadapsar",
      "citizen": "Normal",
      "deposit": "5000",
      "prooftype": "Pan card",
      "docnumber": "AA11AA11AA11",
      "refername": "Deepa",
      "refernumber": "123456789",
      "referaddress": "Pune",
      "cid": "R-142",
      "id": 25
    },
    {
      "name": "",
      "username": "",
      "password": "",
      "guardiantype": "",
      "gname": "",
      "address": "",
      "citizenship": "",
      "inputCountry": 3,
      "state": "",
      "email": "",
      "gender": "",
      "maritialstatus": "",
      "contact": "",
      "dob": "",
      "registerDate": "2021-05-11",
      "accountType": "",
      "branch": "",
      "citizen": "",
      "deposit": "",
      "prooftype": "",
      "docnumber": "",
      "refername": "",
      "refernumber": "",
      "referaddress": "",
      "cid": "R-867",
      "id": 26
    },
    {
      "name": "",
      "username": "",
      "password": "",
      "guardiantype": "",
      "gname": "",
      "address": "",
      "citizenship": "",
      "inputCountry": 3,
      "state": "",
      "email": "",
      "gender": "",
      "maritialstatus": "",
      "contact": "",
      "dob": "",
      "registerDate": "2021-05-11",
      "accountType": "",
      "branch": "",
      "citizen": "",
      "deposit": "",
      "prooftype": "",
      "docnumber": "",
      "refername": "",
      "refernumber": "",
      "referaddress": "",
      "cid": "R-726",
      "id": 27
    },
    {
      "name": "Vishal",
      "username": "vp7860",
      "password": "123456",
      "guardiantype": "Father",
      "gname": "Tejrao",
      "address": "Pune",
      "citizenship": "Indian",
      "inputCountry": "India",
      "state": "Maharashtra",
      "email": "vp@gmail.com",
      "gender": "Male",
      "maritialstatus": "Unmarried",
      "contact": "9090909090",
      "dob": "23-10-1998",
      "registerDate": "11-05-2021",
      "accountType": "Savings",
      "branch": "Hadapsar",
      "citizen": "Normal",
      "deposit": "5000",
      "prooftype": "Pan card",
      "docnumber": "AA11AA11AA11",
      "refername": "Deepa",
      "refernumber": "123456789",
      "referaddress": "Pune",
      "cid": "R-496",
      "id": 28
    },
    {
      "name": "",
      "username": "",
      "password": "",
      "guardiantype": "",
      "gname": "",
      "address": "",
      "citizenship": "",
      "inputCountry": 3,
      "state": "",
      "email": "",
      "gender": "",
      "maritialstatus": "",
      "contact": "",
      "dob": "",
      "registerDate": "2021-05-11",
      "accountType": "",
      "branch": "",
      "citizen": "",
      "deposit": "",
      "prooftype": "",
      "docnumber": "",
      "refername": "",
      "refernumber": "",
      "referaddress": "",
      "cid": "R-871",
      "id": 29
    },
    {
      "name": "",
      "username": "",
      "password": "",
      "guardiantype": "",
      "gname": "",
      "address": "",
      "citizenship": "",
      "inputCountry": 3,
      "state": "",
      "email": "",
      "gender": "",
      "maritialstatus": "",
      "contact": "",
      "dob": "",
      "registerDate": "2021-05-11",
      "accountType": "",
      "branch": "",
      "citizen": "",
      "deposit": "",
      "prooftype": "",
      "docnumber": "",
      "refername": "",
      "refernumber": "",
      "referaddress": "",
      "cid": "R-845",
      "id": 30
    },
    {
      "name": "Vishal",
      "username": "vp7860",
      "password": "123456",
      "guardiantype": "Father",
      "gname": "Tejrao",
      "address": "Pune",
      "citizenship": "Indian",
      "inputCountry": "India",
      "state": "Maharashtra",
      "email": "vp@gmail.com",
      "gender": "Male",
      "maritialstatus": "Unmarried",
      "contact": "9090909090",
      "dob": "23-10-1998",
      "registerDate": "11-05-2021",
      "accountType": "Savings",
      "branch": "Hadapsar",
      "citizen": "Normal",
      "deposit": "5000",
      "prooftype": "Pan card",
      "docnumber": "AA11AA11AA11",
      "refername": "Deepa",
      "refernumber": "123456789",
      "referaddress": "Pune",
      "cid": "R-630",
      "id": 31
    },
    {
      "name": "Vishal",
      "username": "vp7860",
      "password": "123456",
      "guardiantype": "Father",
      "gname": "Tejrao",
      "address": "Pune",
      "citizenship": "Indian",
      "inputCountry": "India",
      "state": "Maharashtra",
      "email": "vp@gmail.com",
      "gender": "Male",
      "maritialstatus": "Unmarried",
      "contact": "9090909090",
      "dob": "23-10-1998",
      "registerDate": "11-05-2021",
      "accountType": "Savings",
      "branch": "Hadapsar",
      "citizen": "Normal",
      "deposit": "5000",
      "prooftype": "Pan card",
      "docnumber": "AA11AA11AA11",
      "refername": "Deepa",
      "refernumber": "123456789",
      "referaddress": "Pune",
      "cid": "R-899",
      "id": 32
    },
    {
      "name": "",
      "username": "",
      "password": "",
      "guardiantype": "",
      "gname": "",
      "address": "",
      "citizenship": "",
      "inputCountry": 3,
      "state": "",
      "email": "",
      "gender": "",
      "maritialstatus": "",
      "contact": "",
      "dob": "",
      "registerDate": "2021-05-11",
      "accountType": "",
      "branch": "",
      "citizen": "",
      "deposit": "",
      "prooftype": "",
      "docnumber": "",
      "refername": "",
      "refernumber": "",
      "referaddress": "",
      "cid": "R-550",
      "id": 33
    },
    {
      "name": "",
      "username": "",
      "password": "",
      "guardiantype": "",
      "gname": "",
      "address": "",
      "citizenship": "",
      "inputCountry": 3,
      "state": "",
      "email": "",
      "gender": "",
      "maritialstatus": "",
      "contact": "",
      "dob": "",
      "registerDate": "2021-05-11",
      "accountType": "",
      "branch": "",
      "citizen": "",
      "deposit": "",
      "prooftype": "",
      "docnumber": "",
      "refername": "",
      "refernumber": "",
      "referaddress": "",
      "cid": "R-252",
      "id": 34
    },
    {
      "name": "Vishal",
      "username": "vp7860",
      "password": "123456",
      "guardiantype": "Father",
      "gname": "Tejrao",
      "address": "Pune",
      "citizenship": "Indian",
      "inputCountry": "India",
      "state": "Maharashtra",
      "email": "vp@gmail.com",
      "gender": "Male",
      "maritialstatus": "Unmarried",
      "contact": "9090909090",
      "dob": "23-10-1998",
      "registerDate": "11-05-2021",
      "accountType": "Savings",
      "branch": "Hadapsar",
      "citizen": "Normal",
      "deposit": "5000",
      "prooftype": "Pan card",
      "docnumber": "AA11AA11AA11",
      "refername": "Deepa",
      "refernumber": "123456789",
      "referaddress": "Pune",
      "cid": "R-759",
      "id": 35
    },
    {
      "name": "",
      "username": "",
      "password": "",
      "guardiantype": "",
      "gname": "",
      "address": "",
      "citizenship": "",
      "inputCountry": 3,
      "state": "",
      "email": "",
      "gender": "",
      "maritialstatus": "",
      "contact": "",
      "dob": "",
      "registerDate": "2021-05-11",
      "accountType": "",
      "branch": "",
      "citizen": "",
      "deposit": "",
      "prooftype": "",
      "docnumber": "",
      "refername": "",
      "refernumber": "",
      "referaddress": "",
      "cid": "R-818",
      "id": 36
    },
    {
      "name": "",
      "username": "",
      "password": "",
      "guardiantype": "",
      "gname": "",
      "address": "",
      "citizenship": "",
      "inputCountry": 3,
      "state": "",
      "email": "",
      "gender": "",
      "maritialstatus": "",
      "contact": "",
      "dob": "",
      "registerDate": "2021-05-11",
      "accountType": "",
      "branch": "",
      "citizen": "",
      "deposit": "",
      "prooftype": "",
      "docnumber": "",
      "refername": "",
      "refernumber": "",
      "referaddress": "",
      "cid": "R-486",
      "id": 37
    },
    {
      "name": "",
      "username": "",
      "password": "",
      "guardiantype": "",
      "gname": "",
      "address": "",
      "citizenship": "",
      "inputCountry": 3,
      "state": "",
      "email": "",
      "gender": "",
      "maritialstatus": "",
      "contact": "",
      "dob": "",
      "registerDate": "2021-05-11",
      "accountType": "",
      "branch": "",
      "citizen": "",
      "deposit": "",
      "prooftype": "",
      "docnumber": "",
      "refername": "",
      "refernumber": "",
      "referaddress": "",
      "cid": "R-998",
      "id": 38
    },
    {
      "name": "",
      "username": "",
      "password": "",
      "guardiantype": "",
      "gname": "",
      "address": "",
      "citizenship": "",
      "inputCountry": 3,
      "state": "",
      "email": "",
      "gender": "",
      "maritialstatus": "",
      "contact": "",
      "dob": "",
      "registerDate": "2021-05-11",
      "accountType": "",
      "branch": "",
      "citizen": "",
      "deposit": "",
      "prooftype": "",
      "docnumber": "",
      "refername": "",
      "refernumber": "",
      "referaddress": "",
      "cid": "R-649",
      "id": 39
    },
    {
      "name": "Vishal",
      "username": "vp7860",
      "password": "123456",
      "guardiantype": "Father",
      "gname": "Tejrao",
      "address": "Pune",
      "citizenship": "Indian",
      "inputCountry": "India",
      "state": "Maharashtra",
      "email": "vp@gmail.com",
      "gender": "Male",
      "maritialstatus": "Unmarried",
      "contact": "9090909090",
      "dob": "23-10-1998",
      "registerDate": "11-05-2021",
      "accountType": "Savings",
      "branch": "Hadapsar",
      "citizen": "Normal",
      "deposit": "5000",
      "prooftype": "Pan card",
      "docnumber": "AA11AA11AA11",
      "refername": "Deepa",
      "refernumber": "123456789",
      "referaddress": "Pune",
      "cid": "R-764",
      "id": 40
    }
  ]
}